Workbook

Sheet Overview
B2: Construction Contract Query Benchmark — 30 Queries (Stratified)
B3: Expanded & diversified evaluation set for ARA (submission COENG-19357)
B5: PURPOSE
B6: Why 30 | C6: Triples the original N=10; gives Friedman/Wilcoxon real power and ~10 per stratum, while staying finishable. Positioned as a credible expert-rated DOMAIN evaluation, not a large ML benchmark.
B7: Stratified design | C7: 10 Simple · 10 Borderline · 10 Complex. The borderline band (±20% of τ) is where routing accuracy stops being a foregone conclusion.
B8: Anchoring | C8: The 10 original queries (Source A) are retained VERBATIM so nothing is wasted; 20 new queries are grounded in two further contracts.
B10: SCORING MODEL (manuscript formula, τ = 15.92)
B11: C(Q) | C11: 1.0·|T| + 2.0·Ops + 1.5·Depth + 1.0·Amb + 2.0·Dom
B12: Route | C12: C(Q) > τ → RAG-Gym (complex); C(Q) ≤ τ → RAG-Flow (simple)
B13: Borderline band | C13: [12.74, 19.10] (τ ± 20%)
B14: |T| | C14: Distinct content terms (stopword-filtered)
B15: Ops | C15: Count of logical operators (and / or / not / without / joins)
B16: Depth | C16: 1 + conditional/nesting markers (if / when / where / whether / unless …)
B17: Amb | C17: Mean −log₁₀ p(t|D) over distinct terms — corpus-dependent
B18: Dom | C18: 1·{multi-domain} + |Domains(Q)| — domain spread
B20: HEADLINE RESULT
B21: Routing accuracy | C21: Simple 100% · Borderline 70% · Complex 100% · Overall 90% — see Routing_Accuracy.
B22: Reading | C22: The 3 borderline misroutes are all true-complex questions scoring just below τ. They are the point: routing is a real metric only near the boundary.
B24: SOURCE CONTRACTS
B25: A | C25: ADB time-based consultancy (Sri Lanka) — original anchored queries.
B26: C | C26: New Bridge over the Kelani River, Steel Bridge Pkg 1, RDA/JICA — FIDIC MDB Harmonised. Measurement vs payment, shop- vs contract-drawings, variations, splice plates, notches/cope holes, transport, determinations (3.5), DB referral (20.1), delayed-payment interest (14.8).
B27: D | C27: Lecture Theatre Complex, Faculty of Science, Univ. of Kelaniya — Design & Build, ICTAD/SBD/04. EOT (8.4) & 42-day determination, Contractor's Claims (19.1), variation procedure (13.3) & verbal-instruction confirmation (3.3), IPC reversal/estoppel, prevention/time-at-large, performance security, advance payment (14.2), design responsibility.
B29: IMPORTANT CAVEATS
B30: Amb is corpus-dependent | C30: Amb here is computed from the two uploaded contracts as a STAND-IN for the deployed corpus_stats.json. Absolute Amb (and borderline placements nearest τ) may shift under the deployed extractor.
B31: Tokenisation unlocked | C31: |T| uses distinct content terms; the exact tokenisation rule is the one flagged by reviewers (|T(Q1)|=4 vs 3) and should be locked in complexity.py for bit-exact reproduction.
B32: Anchored example X01 | C32: The verbatim manuscript Table-1 complex example scores 16.24 under the stand-in extractor — upper borderline, but still routes complex correctly. Not reworded.
B33: Ground truth | C33: GT class is the expert routing label, independent of C(Q). It is what routing accuracy is measured against; borderline GT is deliberately mixed.

Sheet Model
B2: ARA Complexity Model — Editable Parameters
B3: Edit the weights or τ and every score, route and stratum on Benchmark_30 recomputes (τ-sensitivity tool, reviewer pt R2-2).
A5: Weight α — |T| (distinct content terms) | B5: 1
A6: Weight α — Ops (logical operators) | B6: 2
A7: Weight α — Depth (nesting/conditional) | B7: 1.5
A8: Weight α — Amb (mean −log₁₀ p(t|D)) | B8: 1
A9: Weight α — Dom (domain spread) | B9: 2
A10: Routing threshold τ | B10: 15.92
A11: Borderline band lower = τ × 0.8 | B11: =B10*0.8 -> 12.736
A12: Borderline band upper = τ × 1.2 | B12: =B10*1.2 -> 19.104

Sheet Benchmark_30
A1: Construction Contract Query Benchmark — 30 queries (stratified)
A2: Sources: A = ADB consultancy (anchored originals) · C = Kelani River steel bridge DB referral (FIDIC MDB) · D = Univ. of Kelaniya Lecture Theatre, Design & Build (ICTAD/SBD/04)
A4: ID | B4: Intended Stratum | C4: Clause Type | D4: Src | E4: Anchored | F4: Query | G4: |T| | H4: Ops | I4: Depth | J4: Amb | K4: Dom | L4: C(Q) | M4: Route | N4: Landed Band | O4: GT Class | P4: Router Correct
A5: S01 | B5: simple | C5: Time / Commencement | D5: A | E5: Yes | F5: What is the project commencement date? | G5: 3 | H5: 0 | I5: 1 | J5: 3.087 | K5: 1 | L5: =G5*Model!$B$5+H5*Model!$B$6+I5*Model!$B$7+J5*Model!$B$8+K5*Model!$B$9 -> 9.587 | M5: =IF(L5>Model!$B$10,"RAG-Gym","RAG-Flow") -> RAG-Flow | N5: =IF(L5<Model!$B$11,"Simple",IF(L5>Model!$B$12,"Complex","Borderline")) -> Simple | O5: simple | P5: =IF(IF(L5>Model!$B$10,"complex","simple")=O5,1,0) -> 1
A6: S02 | B6: simple | C6: Defects Liability | D6: A | E6: Yes | F6: What is the defects liability period? | G6: 3 | H6: 0 | I6: 1 | J6: 3.797 | K6: 1 | L6: =G6*Model!$B$5+H6*Model!$B$6+I6*Model!$B$7+J6*Model!$B$8+K6*Model!$B$9 -> 10.297 | M6: =IF(L6>Model!$B$10,"RAG-Gym","RAG-Flow") -> RAG-Flow | N6: =IF(L6<Model!$B$11,"Simple",IF(L6>Model!$B$12,"Complex","Borderline")) -> Simple | O6: simple | P6: =IF(IF(L6>Model!$B$10,"complex","simple")=O6,1,0) -> 1
A7: S03 | B7: simple | C7: Payment / Retention | D7: A | E7: Yes | F7: What is the retention percentage under the contract? | G7: 3 | H7: 0 | I7: 1 | J7: 3.398 | K7: 1 | L7: =G7*Model!$B$5+H7*Model!$B$6+I7*Model!$B$7+J7*Model!$B$8+K7*Model!$B$9 -> 9.898 | M7: =IF(L7>Model!$B$10,"RAG-Gym","RAG-Flow") -> RAG-Flow | N7: =IF(L7<Model!$B$11,"Simple",IF(L7>Model!$B$12,"Complex","Borderline")) -> Simple | O7: simple | P7: =IF(IF(L7>Model!$B$10,"complex","simple")=O7,1,0) -> 1
A8: S04 | B8: simple | C8: Security / Performance Bond | D8: A | E8: Yes | F8: What is the value of the performance bond? | G8: 3 | H8: 0 | I8: 1 | J8: 3.904 | K8: 1 | L8: =G8*Model!$B$5+H8*Model!$B$6+I8*Model!$B$7+J8*Model!$B$8+K8*Model!$B$9 -> 10.404 | M8: =IF(L8>Model!$B$10,"RAG-Gym","RAG-Flow") -> RAG-Flow | N8: =IF(L8<Model!$B$11,"Simple",IF(L8>Model!$B$12,"Complex","Borderline")) -> Simple | O8: simple | P8: =IF(IF(L8>Model!$B$10,"complex","simple")=O8,1,0) -> 1
A9: S05 | B9: simple | C9: Time / Liquidated Damages | D9: A | E9: Yes | F9: What is the liquidated damages rate per day? | G9: 4 | H9: 0 | I9: 1 | J9: 3.547 | K9: 1 | L9: =G9*Model!$B$5+H9*Model!$B$6+I9*Model!$B$7+J9*Model!$B$8+K9*Model!$B$9 -> 11.047 | M9: =IF(L9>Model!$B$10,"RAG-Gym","RAG-Flow") -> RAG-Flow | N9: =IF(L9<Model!$B$11,"Simple",IF(L9>Model!$B$12,"Complex","Borderline")) -> Simple | O9: simple | P9: =IF(IF(L9>Model!$B$10,"complex","simple")=O9,1,0) -> 1
A10: S06 | B10: simple | C10: Payment / Contract Price | D10: D | E10: — | F10: What is the Contract Price stated in the agreement? | G10: 4 | H10: 0 | I10: 1 | J10: 2.918 | K10: 1 | L10: =G10*Model!$B$5+H10*Model!$B$6+I10*Model!$B$7+J10*Model!$B$8+K10*Model!$B$9 -> 10.418 | M10: =IF(L10>Model!$B$10,"RAG-Gym","RAG-Flow") -> RAG-Flow | N10: =IF(L10<Model!$B$11,"Simple",IF(L10>Model!$B$12,"Complex","Borderline")) -> Simple | O10: simple | P10: =IF(IF(L10>Model!$B$10,"complex","simple")=O10,1,0) -> 1
A11: S07 | B11: simple | C11: Security / Performance Security | D11: D | E11: — | F11: What percentage is the Performance Security? | G11: 3 | H11: 0 | I11: 1 | J11: 3.904 | K11: 1 | L11: =G11*Model!$B$5+H11*Model!$B$6+I11*Model!$B$7+J11*Model!$B$8+K11*Model!$B$9 -> 10.404 | M11: =IF(L11>Model!$B$10,"RAG-Gym","RAG-Flow") -> RAG-Flow | N11: =IF(L11<Model!$B$11,"Simple",IF(L11>Model!$B$12,"Complex","Borderline")) -> Simple | O11: simple | P11: =IF(IF(L11>Model!$B$10,"complex","simple")=O11,1,0) -> 1
A12: S08 | B12: simple | C12: Measurement / Steel Weight | D12: C | E12: — | F12: What unit weight of steel is assumed in the contract? | G12: 5 | H12: 0 | I12: 1 | J12: 3.028 | K12: 1 | L12: =G12*Model!$B$5+H12*Model!$B$6+I12*Model!$B$7+J12*Model!$B$8+K12*Model!$B$9 -> 11.528 | M12: =IF(L12>Model!$B$10,"RAG-Gym","RAG-Flow") -> RAG-Flow | N12: =IF(L12<Model!$B$11,"Simple",IF(L12>Model!$B$12,"Complex","Borderline")) -> Simple | O12: simple | P12: =IF(IF(L12>Model!$B$10,"complex","simple")=O12,1,0) -> 1
A13: S09 | B13: simple | C13: Time / EOT Determination | D13: D | E13: — | F13: What is the time limit for assessing an extension of time? | G13: 4 | H13: 0 | I13: 1 | J13: 3.322 | K13: 1 | L13: =G13*Model!$B$5+H13*Model!$B$6+I13*Model!$B$7+J13*Model!$B$8+K13*Model!$B$9 -> 10.822 | M13: =IF(L13>Model!$B$10,"RAG-Gym","RAG-Flow") -> RAG-Flow | N13: =IF(L13<Model!$B$11,"Simple",IF(L13>Model!$B$12,"Complex","Borderline")) -> Simple | O13: simple | P13: =IF(IF(L13>Model!$B$10,"complex","simple")=O13,1,0) -> 1
A14: S10 | B14: simple | C14: Measurement / Drawings | D14: C | E14: — | F14: From which drawings are the computed weights taken? | G14: 4 | H14: 0 | I14: 1 | J14: 3.046 | K14: 1 | L14: =G14*Model!$B$5+H14*Model!$B$6+I14*Model!$B$7+J14*Model!$B$8+K14*Model!$B$9 -> 10.546 | M14: =IF(L14>Model!$B$10,"RAG-Gym","RAG-Flow") -> RAG-Flow | N14: =IF(L14<Model!$B$11,"Simple",IF(L14>Model!$B$12,"Complex","Borderline")) -> Simple | O14: simple | P14: =IF(IF(L14>Model!$B$10,"complex","simple")=O14,1,0) -> 1
A15: B01 | B15: borderline | C15: Measurement / Splice Plates | D15: C | E15: — | F15: Are splice plates that replaced welded joints measured for payment? | G15: 7 | H15: 0 | I15: 1 | J15: 2.761 | K15: 3 | L15: =G15*Model!$B$5+H15*Model!$B$6+I15*Model!$B$7+J15*Model!$B$8+K15*Model!$B$9 -> 17.261 | M15: =IF(L15>Model!$B$10,"RAG-Gym","RAG-Flow") -> RAG-Gym | N15: =IF(L15<Model!$B$11,"Simple",IF(L15>Model!$B$12,"Complex","Borderline")) -> Borderline | O15: complex | P15: =IF(IF(L15>Model!$B$10,"complex","simple")=O15,1,0) -> 1
A16: B02 | B16: borderline | C16: Measurement / Shop Drawings | D16: C | E16: — | F16: Can the contractor's approved shop drawings be used as the basis for measurement? | G16: 7 | H16: 0 | I16: 1 | J16: 2.413 | K16: 1 | L16: =G16*Model!$B$5+H16*Model!$B$6+I16*Model!$B$7+J16*Model!$B$8+K16*Model!$B$9 -> 12.913 | M16: =IF(L16>Model!$B$10,"RAG-Gym","RAG-Flow") -> RAG-Flow | N16: =IF(L16<Model!$B$11,"Simple",IF(L16>Model!$B$12,"Complex","Borderline")) -> Borderline | O16: complex | P16: =IF(IF(L16>Model!$B$10,"complex","simple")=O16,1,0) -> 0
... A34: X10 | B34: complex | C34: Payment / Estoppel & Remedy | D34: D | E34: — | F34: Where the employer's late site possession caused cost escalation that the employer partly approved but the engineer later reversed across several certificates, can the reversal be sustained and what estoppel and remedy arguments apply? | G34: 21 | H34: 2 | I34: 2 | J34: 3.586 | K34: 3 | L34: =G34*Model!$B$5+H34*Model!$B$6+I34*Model!$B$7+J34*Model!$B$8+K34*Model!$B$9 -> 37.586 | M34: =IF(L34>Model!$B$10,"RAG-Gym","RAG-Flow") -> RAG-Gym | N34: =IF(L34<Model!$B$11,"Simple",IF(L34>Model!$B$12,"Complex","Borderline")) -> Complex | O34: complex | P34: =IF(IF(L34>Model!$B$10,"complex","simple")=O34,1,0) -> 1

Sheet Routing_Accuracy
A1: Routing Accuracy by Stratum
A2: Router class = sign of C(Q) vs τ. Ground-truth class = expert label. Accuracy = share where they agree.
A4: Stratum | B4: n | C4: Router Correct | D4: Accuracy | E4: Note
A5: Simple | B5: =COUNTIF(Benchmark_30!$B$5:$B$34,"simple") -> 10 | C5: =SUMIFS(Benchmark_30!$P$5:$P$34,Benchmark_30!$B$5:$B$34,"simple") -> 10 | D5: =C5/B5 -> 1 | E5: Clear lookups — router decision trivial.
A6: Borderline | B6: =COUNTIF(Benchmark_30!$B$5:$B$34,"borderline") -> 10 | C6: =SUMIFS(Benchmark_30!$P$5:$P$34,Benchmark_30!$B$5:$B$34,"borderline") -> 7 | D6: =C6/B6 -> 0.7 | E6: Near τ — where routing is a genuine, non-trivial test.
A7: Complex | B7: =COUNTIF(Benchmark_30!$B$5:$B$34,"complex") -> 10 | C7: =SUMIFS(Benchmark_30!$P$5:$P$34,Benchmark_30!$B$5:$B$34,"complex") -> 10 | D7: =C7/B7 -> 1 | E7: Clear multi-clause reasoning — router decision trivial.
A8: Overall | B8: =SUM(B5:B7) -> 30 | C8: =SUM(C5:C7) -> 27 | D8: =C8/B8 -> 0.9

Sheet Clause_Coverage
A1: Clause-Type & Source Coverage
A2: Demonstrates diversity beyond the original payment/dispute pair (reviewer pt R2-1: larger AND more diverse).
A4: Clause Family | B4: Queries | C4: Count
A5: Defects Liability | B5: S02 | C5: 1
A6: Dispute | B6: X02 | C6: 1
A7: Measurement | B7: S08, S10, B01, B02, B05, X06, X09 | C7: 7
A8: Payment | B8: S03, S06, B03, B09, X10 | C8: 5
A9: Security | B9: S04, S07, B07 | C9: 3
A10: Termination | B10: X05 | C10: 1
A11: Time | B11: S01, S05, S09, B06, B08, X01, X04, X07 | C11: 8
A12: Variation | B12: B04, B10, X03, X08 | C12: 4
A13: 8 clause families | C13: =SUM(C5:C12) -> 30
A15: Source contracts
A16: A — ADB consultancy (anchored originals) | B16: 10
A17: B — Kelani River steel bridge (FIDIC MDB) | B17: 9
A18: C — Statement of Claim prepared based on Conditions of ICTAD/CIDA SBD/04 | B18: 11
